LICENSE
README.md
setup.py
slurmjobs/__init__.py
slurmjobs/__main__.py
slurmjobs/__version__.py
slurmjobs/args.py
slurmjobs/core.py
slurmjobs/grid.py
slurmjobs/receipt.py
slurmjobs/util.py
slurmjobs.egg-info/PKG-INFO
slurmjobs.egg-info/SOURCES.txt
slurmjobs.egg-info/dependency_links.txt
slurmjobs.egg-info/requires.txt
slurmjobs.egg-info/top_level.txt
slurmjobs/templates/job.base.j2
slurmjobs/templates/job.sbatch.j2
slurmjobs/templates/job.shell.j2
slurmjobs/templates/job.singularity.j2
slurmjobs/templates/run.base.j2
slurmjobs/templates/run.sbatch.j2