Metadata-Version: 2.1
Name: slurmjobs
Version: 1.1.0
Summary: Generate slurm jobs in batches.
Home-page: UNKNOWN
Author: Bea Steers
Author-email: bea.steers@gmail.com
License: # slurmjobs
Keywords: slurm sbatch job batch generation parameters ml machine learning python
Platform: UNKNOWN
Provides-Extra: test
Provides-Extra: doc
